[{"depth": 6,
"num_channels": 64,
"activation_function": "<class 'torch.nn.modules.activation.ReLU'>",
"kernel_size": 3,
"lr_pretrain": 0.001,
"lr_fine_tune": 0.001,
"num_train": 10,
"early_stop_patience": 5,
"save_best": false,
"save_checkpoints": false,
"is_cnn": true,
"is_debug": false,
"classification_report_flag": false,
"batch_size": 64,
"pre_train_classes": [5, 6, 7, 8, 9],
"fine_tune_classes": [2, 3, 0, 1],
"val_split": 0.1,
"num_workers": 0,
"generate_dataset_seed": 42,
"use_pooling": true,
"pooling_every_n_layers": 2,
"pooling_stride": 2,
"freeze": true,
"reinit": true,
"reinit_both_dense": true,
"truncate": false},
{"lr": 0.001,
  "sampled_percentage": 0.001,
  "sampled_cut_point": -1,
  "repeat": 0,
  "train_acc": 0.75,
  "test_acc": 0.29875},
 {"lr": 0.001,
  "sampled_percentage": 0.001,
  "sampled_cut_point": -1,
  "repeat": 1,
  "train_acc": 0.8125,
  "test_acc": 0.337},
 {"lr": 0.001,
  "sampled_percentage": 0.001,
  "sampled_cut_point": -1,
  "repeat": 2,
  "train_acc": 0.5,
  "test_acc": 0.29075},
 {"lr": 0.001,
  "sampled_percentage": 0.001,
  "sampled_cut_point": -1,
  "repeat": 3,
  "train_acc": 0.625,
  "test_acc": 0.385},
 {"lr": 0.001,
  "sampled_percentage": 0.001,
  "sampled_cut_point": -1,
  "repeat": 4,
  "train_acc": 0.375,
  "test_acc": 0.269},
 {"lr": 0.001,
  "sampled_percentage": 0.001,
  "sampled_cut_point": -1,
  "repeat": 5,
  "train_acc": 0.5625,
  "test_acc": 0.30775},
 {"lr": 0.001,
  "sampled_percentage": 0.001,
  "sampled_cut_point": -1,
  "repeat": 6,
  "train_acc": 0.8125,
  "test_acc": 0.408},
 {"lr": 0.001,
  "sampled_percentage": 0.001,
  "sampled_cut_point": -1,
  "repeat": 7,
  "train_acc": 0.875,
  "test_acc": 0.3115},
 {"lr": 0.001,
  "sampled_percentage": 0.001,
  "sampled_cut_point": -1,
  "repeat": 8,
  "train_acc": 0.75,
  "test_acc": 0.4055},
 {"lr": 0.001,
  "sampled_percentage": 0.001,
  "sampled_cut_point": -1,
  "repeat": 9,
  "train_acc": 0.75,
  "test_acc": 0.28575},
 {"lr": 0.001,
  "sampled_percentage": 0.001,
  "sampled_cut_point": -1,
  "repeat": 10,
  "train_acc": 0.625,
  "test_acc": 0.4095},
 {"lr": 0.001,
  "sampled_percentage": 0.001,
  "sampled_cut_point": -1,
  "repeat": 11,
  "train_acc": 0.4375,
  "test_acc": 0.35475},
 {"lr": 0.001,
  "sampled_percentage": 0.001,
  "sampled_cut_point": -1,
  "repeat": 12,
  "train_acc": 0.5625,
  "test_acc": 0.398},
 {"lr": 0.001,
  "sampled_percentage": 0.001,
  "sampled_cut_point": -1,
  "repeat": 13,
  "train_acc": 0.6875,
  "test_acc": 0.416},
 {"lr": 0.001,
  "sampled_percentage": 0.001,
  "sampled_cut_point": -1,
  "repeat": 14,
  "train_acc": 0.625,
  "test_acc": 0.406},
 {"lr": 0.001,
  "sampled_percentage": 0.001,
  "sampled_cut_point": -1,
  "repeat": 15,
  "train_acc": 0.375,
  "test_acc": 0.32625},
 {"lr": 0.001,
  "sampled_percentage": 0.001,
  "sampled_cut_point": -1,
  "repeat": 16,
  "train_acc": 0.375,
  "test_acc": 0.28},
 {"lr": 0.001,
  "sampled_percentage": 0.001,
  "sampled_cut_point": -1,
  "repeat": 17,
  "train_acc": 0.6875,
  "test_acc": 0.40875},
 {"lr": 0.001,
  "sampled_percentage": 0.001,
  "sampled_cut_point": -1,
  "repeat": 18,
  "train_acc": 0.5625,
  "test_acc": 0.39525},
 {"lr": 0.001,
  "sampled_percentage": 0.001,
  "sampled_cut_point": -1,
  "repeat": 19,
  "train_acc": 0.8125,
  "test_acc": 0.3875},
 {"lr": 0.001,
  "sampled_percentage": 0.001,
  "sampled_cut_point": -1,
  "repeat": 20,
  "train_acc": 0.9375,
  "test_acc": 0.29425},
 {"lr": 0.001,
  "sampled_percentage": 0.001,
  "sampled_cut_point": -1,
  "repeat": 21,
  "train_acc": 0.75,
  "test_acc": 0.349},
 {"lr": 0.001,
  "sampled_percentage": 0.001,
  "sampled_cut_point": -1,
  "repeat": 22,
  "train_acc": 0.875,
  "test_acc": 0.27225},
 {"lr": 0.001,
  "sampled_percentage": 0.001,
  "sampled_cut_point": -1,
  "repeat": 23,
  "train_acc": 0.6875,
  "test_acc": 0.3565},
 {"lr": 0.001,
  "sampled_percentage": 0.001,
  "sampled_cut_point": -1,
  "repeat": 24,
  "train_acc": 0.9375,
  "test_acc": 0.367},
 {"lr": 0.001,
  "sampled_percentage": 0.01,
  "sampled_cut_point": -1,
  "repeat": 0,
  "train_acc": 0.5111111111111111,
  "test_acc": 0.4205},
 {"lr": 0.001,
  "sampled_percentage": 0.01,
  "sampled_cut_point": -1,
  "repeat": 1,
  "train_acc": 0.5388888888888889,
  "test_acc": 0.49125},
 {"lr": 0.001,
  "sampled_percentage": 0.01,
  "sampled_cut_point": -1,
  "repeat": 2,
  "train_acc": 0.5444444444444444,
  "test_acc": 0.4325},
 {"lr": 0.001,
  "sampled_percentage": 0.01,
  "sampled_cut_point": -1,
  "repeat": 3,
  "train_acc": 0.6222222222222222,
  "test_acc": 0.48225},
 {"lr": 0.001,
  "sampled_percentage": 0.01,
  "sampled_cut_point": -1,
  "repeat": 4,
  "train_acc": 0.5944444444444444,
  "test_acc": 0.484},
 {"lr": 0.001,
  "sampled_percentage": 0.01,
  "sampled_cut_point": -1,
  "repeat": 5,
  "train_acc": 0.5277777777777778,
  "test_acc": 0.44025},
 {"lr": 0.001,
  "sampled_percentage": 0.01,
  "sampled_cut_point": -1,
  "repeat": 6,
  "train_acc": 0.5444444444444444,
  "test_acc": 0.4485},
 {"lr": 0.001,
  "sampled_percentage": 0.01,
  "sampled_cut_point": -1,
  "repeat": 7,
  "train_acc": 0.5388888888888889,
  "test_acc": 0.48025},
 {"lr": 0.001,
  "sampled_percentage": 0.01,
  "sampled_cut_point": -1,
  "repeat": 8,
  "train_acc": 0.5888888888888889,
  "test_acc": 0.4865},
 {"lr": 0.001,
  "sampled_percentage": 0.01,
  "sampled_cut_point": -1,
  "repeat": 9,
  "train_acc": 0.5333333333333333,
  "test_acc": 0.48175},
 {"lr": 0.001,
  "sampled_percentage": 0.01,
  "sampled_cut_point": -1,
  "repeat": 10,
  "train_acc": 0.5444444444444444,
  "test_acc": 0.466},
 {"lr": 0.001,
  "sampled_percentage": 0.01,
  "sampled_cut_point": -1,
  "repeat": 11,
  "train_acc": 0.5777777777777777,
  "test_acc": 0.467},
 {"lr": 0.001,
  "sampled_percentage": 0.01,
  "sampled_cut_point": -1,
  "repeat": 12,
  "train_acc": 0.5777777777777777,
  "test_acc": 0.47475},
 {"lr": 0.001,
  "sampled_percentage": 0.01,
  "sampled_cut_point": -1,
  "repeat": 13,
  "train_acc": 0.5388888888888889,
  "test_acc": 0.507},
 {"lr": 0.001,
  "sampled_percentage": 0.01,
  "sampled_cut_point": -1,
  "repeat": 14,
  "train_acc": 0.5277777777777778,
  "test_acc": 0.4725},
 {"lr": 0.001,
  "sampled_percentage": 0.01,
  "sampled_cut_point": -1,
  "repeat": 15,
  "train_acc": 0.5666666666666667,
  "test_acc": 0.47875},
 {"lr": 0.001,
  "sampled_percentage": 0.01,
  "sampled_cut_point": -1,
  "repeat": 16,
  "train_acc": 0.6944444444444444,
  "test_acc": 0.51175},
 {"lr": 0.001,
  "sampled_percentage": 0.01,
  "sampled_cut_point": -1,
  "repeat": 17,
  "train_acc": 0.55,
  "test_acc": 0.49},
 {"lr": 0.001,
  "sampled_percentage": 0.01,
  "sampled_cut_point": -1,
  "repeat": 18,
  "train_acc": 0.5277777777777778,
  "test_acc": 0.442},
 {"lr": 0.001,
  "sampled_percentage": 0.01,
  "sampled_cut_point": -1,
  "repeat": 19,
  "train_acc": 0.48333333333333334,
  "test_acc": 0.46175},
 {"lr": 0.001,
  "sampled_percentage": 0.01,
  "sampled_cut_point": -1,
  "repeat": 20,
  "train_acc": 0.5833333333333334,
  "test_acc": 0.48625},
 {"lr": 0.001,
  "sampled_percentage": 0.01,
  "sampled_cut_point": -1,
  "repeat": 21,
  "train_acc": 0.5944444444444444,
  "test_acc": 0.5145},
 {"lr": 0.001,
  "sampled_percentage": 0.01,
  "sampled_cut_point": -1,
  "repeat": 22,
  "train_acc": 0.5777777777777777,
  "test_acc": 0.48725},
 {"lr": 0.001,
  "sampled_percentage": 0.01,
  "sampled_cut_point": -1,
  "repeat": 23,
  "train_acc": 0.5777777777777777,
  "test_acc": 0.44625},
 {"lr": 0.001,
  "sampled_percentage": 0.01,
  "sampled_cut_point": -1,
  "repeat": 24,
  "train_acc": 0.5944444444444444,
  "test_acc": 0.5345},
 {"lr": 0.001,
  "sampled_percentage": 0.1,
  "sampled_cut_point": -1,
  "repeat": 0,
  "train_acc": 0.7716666666666666,
  "test_acc": 0.67725},
 {"lr": 0.001,
  "sampled_percentage": 0.1,
  "sampled_cut_point": -1,
  "repeat": 1,
  "train_acc": 0.7733333333333333,
  "test_acc": 0.7055},
 {"lr": 0.001,
  "sampled_percentage": 0.1,
  "sampled_cut_point": -1,
  "repeat": 2,
  "train_acc": 0.7505555555555555,
  "test_acc": 0.7095},
 {"lr": 0.001,
  "sampled_percentage": 0.1,
  "sampled_cut_point": -1,
  "repeat": 3,
  "train_acc": 0.7827777777777778,
  "test_acc": 0.72675},
 {"lr": 0.001,
  "sampled_percentage": 0.1,
  "sampled_cut_point": -1,
  "repeat": 4,
  "train_acc": 0.725,
  "test_acc": 0.692},
 {"lr": 0.001,
  "sampled_percentage": 0.1,
  "sampled_cut_point": -1,
  "repeat": 5,
  "train_acc": 0.7522222222222222,
  "test_acc": 0.69075},
 {"lr": 0.001,
  "sampled_percentage": 0.1,
  "sampled_cut_point": -1,
  "repeat": 6,
  "train_acc": 0.7644444444444445,
  "test_acc": 0.6705},
 {"lr": 0.001,
  "sampled_percentage": 0.1,
  "sampled_cut_point": -1,
  "repeat": 7,
  "train_acc": 0.8027777777777778,
  "test_acc": 0.71225},
 {"lr": 0.001,
  "sampled_percentage": 0.1,
  "sampled_cut_point": -1,
  "repeat": 8,
  "train_acc": 0.7794444444444445,
  "test_acc": 0.722},
 {"lr": 0.001,
  "sampled_percentage": 0.1,
  "sampled_cut_point": -1,
  "repeat": 9,
  "train_acc": 0.6838888888888889,
  "test_acc": 0.64},
 {"lr": 0.001,
  "sampled_percentage": 0.1,
  "sampled_cut_point": -1,
  "repeat": 10,
  "train_acc": 0.71,
  "test_acc": 0.6655},
 {"lr": 0.001,
  "sampled_percentage": 0.1,
  "sampled_cut_point": -1,
  "repeat": 11,
  "train_acc": 0.7422222222222222,
  "test_acc": 0.686},
 {"lr": 0.001,
  "sampled_percentage": 0.1,
  "sampled_cut_point": -1,
  "repeat": 12,
  "train_acc": 0.7544444444444445,
  "test_acc": 0.68525},
 {"lr": 0.001,
  "sampled_percentage": 0.1,
  "sampled_cut_point": -1,
  "repeat": 13,
  "train_acc": 0.7733333333333333,
  "test_acc": 0.71775},
 {"lr": 0.001,
  "sampled_percentage": 0.1,
  "sampled_cut_point": -1,
  "repeat": 14,
  "train_acc": 0.7816666666666666,
  "test_acc": 0.70825},
 {"lr": 0.001,
  "sampled_percentage": 0.1,
  "sampled_cut_point": -1,
  "repeat": 15,
  "train_acc": 0.7761111111111111,
  "test_acc": 0.69975},
 {"lr": 0.001,
  "sampled_percentage": 0.1,
  "sampled_cut_point": -1,
  "repeat": 16,
  "train_acc": 0.7611111111111111,
  "test_acc": 0.7045},
 {"lr": 0.001,
  "sampled_percentage": 0.1,
  "sampled_cut_point": -1,
  "repeat": 17,
  "train_acc": 0.765,
  "test_acc": 0.7055},
 {"lr": 0.001,
  "sampled_percentage": 0.1,
  "sampled_cut_point": -1,
  "repeat": 18,
  "train_acc": 0.7544444444444445,
  "test_acc": 0.705},
 {"lr": 0.001,
  "sampled_percentage": 0.1,
  "sampled_cut_point": -1,
  "repeat": 19,
  "train_acc": 0.775,
  "test_acc": 0.706},
 {"lr": 0.001,
  "sampled_percentage": 0.5,
  "sampled_cut_point": -1,
  "repeat": 0,
  "train_acc": 0.8865555555555555,
  "test_acc": 0.8025},
 {"lr": 0.001,
  "sampled_percentage": 0.5,
  "sampled_cut_point": -1,
  "repeat": 1,
  "train_acc": 0.8905555555555555,
  "test_acc": 0.7965},
 {"lr": 0.001,
  "sampled_percentage": 0.5,
  "sampled_cut_point": -1,
  "repeat": 2,
  "train_acc": 0.8706666666666667,
  "test_acc": 0.79575},
 {"lr": 0.001,
  "sampled_percentage": 0.5,
  "sampled_cut_point": -1,
  "repeat": 3,
  "train_acc": 0.8634444444444445,
  "test_acc": 0.8025},
 {"lr": 0.001,
  "sampled_percentage": 0.5,
  "sampled_cut_point": -1,
  "repeat": 4,
  "train_acc": 0.8512222222222222,
  "test_acc": 0.78325},
 {"lr": 0.001,
  "sampled_percentage": 1,
  "sampled_cut_point": -1,
  "repeat": 0,
  "train_acc": 0.9082149818991925,
  "test_acc": 0.84325},
 {"lr": 0.001,
  "sampled_percentage": 1,
  "sampled_cut_point": -1,
  "repeat": 1,
  "train_acc": 0.92046783625731,
  "test_acc": 0.846},
 {"lr": 0.001,
  "sampled_percentage": 1,
  "sampled_cut_point": -1,
  "repeat": 2,
  "train_acc": 0.9157894736842105,
  "test_acc": 0.858},
 {"lr": 0.001,
  "sampled_percentage": 1,
  "sampled_cut_point": -1,
  "repeat": 3,
  "train_acc": 0.9153996101364522,
  "test_acc": 0.8445},
 {"lr": 0.001,
  "sampled_percentage": 1,
  "sampled_cut_point": -1,
  "repeat": 4,
  "train_acc": 0.8927875243664717,
  "test_acc": 0.82925}]